setup.py
jupytoc/__init__.py
jupytoc/cli.py
jupytoc/jupytoc.py
jupytoc/util.py
jupytoc.egg-info/PKG-INFO
jupytoc.egg-info/SOURCES.txt
jupytoc.egg-info/dependency_links.txt
jupytoc.egg-info/entry_points.txt
jupytoc.egg-info/not-zip-safe
jupytoc.egg-info/requires.txt
jupytoc.egg-info/top_level.txt
tests/__init__.py
tests/test_cli.py
tests/test_util.py