Metadata-Version: 1.1
Name: jupytoc
Version: 0.1.4
Summary: A commmand-line interface to add or update TOC to Jupyter Notebooks
Home-page: https://github.com/axelbellec/jupytoc/
Author: axelbellec
Author-email: axel.bellec@outlook.fr
License: MIT
Download-URL: https://github.com/axelbellec/Jupytoc/archive/0.1.4.tar.gz
Keywords: jupytoc cli command line pip jupyter notebook tool
Platform: any
Classifier: Programming Language :: Python :: 3
Classifier: Programming Language :: Python :: 3.3
Classifier: Programming Language :: Python :: 3.4
Classifier: Programming Language :: Python :: 3.5
Classifier: Intended Audience :: Developers
Classifier: License :: OSI Approved :: MIT License
